linksentry/__init__.py
linksentry/cli.py
linksentry/extractor.py
linksentry/model.py
linksentry/predictor.py
linksentry/preprocess.py
linksentry/train.py
linksentry/models/phishing_rf_model.pkl
linksentry-0.1.1.dist-info/licenses/LICENSE
linksentry-0.1.1.dist-info/METADATA
linksentry-0.1.1.dist-info/WHEEL
linksentry-0.1.1.dist-info/entry_points.txt
linksentry-0.1.1.dist-info/top_level.txt
linksentry-0.1.1.dist-info/RECORD
