Metadata-Version: 2.4
Name: linksentry
Version: 0.1.1
Summary: A CLI tool to detect phishing URLs using machine learning
Author: Ronak
License: MIT
Project-URL: Homepage, https://github.com/ronak/linksentry
Project-URL: Repository, https://github.com/ronak/linksentry
Project-URL: Issues, https://github.com/ronak/linksentry/issues
Keywords: phishing,url,security,machine-learning,cli
Classifier: Development Status :: 4 - Beta
Classifier: Environment :: Console
Classifier: Intended Audience :: Developers
Classifier: Intended Audience :: Information Technology
Classifier: Intended Audience :: System Administrators
Classifier: License :: OSI Approved :: MIT License
Classifier: Operating System :: OS Independent
Classifier: Programming Language :: Python :: 3
Classifier: Programming Language :: Python :: 3.9
Classifier: Programming Language :: Python :: 3.10
Classifier: Programming Language :: Python :: 3.11
Classifier: Programming Language :: Python :: 3.12
Classifier: Programming Language :: Python :: 3.13
Classifier: Topic :: Security
Classifier: Topic :: Internet :: WWW/HTTP
Classifier: Topic :: Utilities
Requires-Python: >=3.9
License-File: LICENSE
Requires-Dist: click>=8.0
Requires-Dist: pandas>=1.3
Requires-Dist: scikit-learn>=1.0
Requires-Dist: joblib>=1.0
Requires-Dist: requests>=2.25
Provides-Extra: full
Requires-Dist: dnspython>=2.0; extra == "full"
Requires-Dist: python-whois>=0.8; extra == "full"
Provides-Extra: dev
Requires-Dist: pytest>=7.0; extra == "dev"
Requires-Dist: pytest-cov>=4.0; extra == "dev"
Requires-Dist: black>=23.0; extra == "dev"
Requires-Dist: ruff>=0.1; extra == "dev"
Dynamic: license-file
